random_container_with_url_info/__init__.py
random_container_with_url_info/data.py
random_container_with_url_info-0.0.2.dist-info/licenses/LICENSE
random_container_with_url_info-0.0.2.dist-info/METADATA
random_container_with_url_info-0.0.2.dist-info/WHEEL
random_container_with_url_info-0.0.2.dist-info/top_level.txt
random_container_with_url_info-0.0.2.dist-info/RECORD
