Metadata-Version: 2.4
Name: random_container_with_url_info
Version: 0.0.2
Summary: random_container_with_url_info
Home-page: https://codeberg.org/matkoniecz/random_container_with_url_info
Author: Mateusz Konieczny
Author-email: matkoniecz@tutanota.com
License: MIT
Classifier: Programming Language :: Python :: 3
Classifier: Operating System :: OS Independent
License-File: LICENSE
Dynamic: author
Dynamic: author-email
Dynamic: classifier
Dynamic: description
Dynamic: description-content-type
Dynamic: home-page
Dynamic: license
Dynamic: license-file
Dynamic: summary
